hyrontools/__init__.py
hyrontools/__main__.py
hyrontools/argument_parse_result.py
hyrontools/console.py
hyrontools/executor.py
hyrontools/helpers.py
hyrontools/assets/cli_breakline.txt
hyrontools/assets/cli_header.txt
hyrontools/errors/__init__.py
hyrontools/errors/exec.py
hyrontools/errors/runtime.py
hyrontools/errors/syntax.py
hyrontools/errors/validation.py
hyrontools/operations/__init__.py
hyrontools/operations/operation.py
hyrontools/operations/render.py
hyrontools/operations/renderers.py
hyrontools/operations/s3publish.py
hyrontools/operations/test.py
hyrontools/operations/travisprefixgen.py
hyrontools-1.0.2.dist-info/LICENSE
hyrontools-1.0.2.dist-info/METADATA
hyrontools-1.0.2.dist-info/WHEEL
hyrontools-1.0.2.dist-info/entry_points.txt
hyrontools-1.0.2.dist-info/top_level.txt
hyrontools-1.0.2.dist-info/RECORD
