Metadata-Version: 2.1
Name: hyrontools
Version: 1.0.2
Summary: Hyron CLI Tools
Home-page: https://github.com/jacobneiltaylor/hyrontools
Author: Jacob Neil Taylor
Author-email: me@jacobtaylor.id.au
License: UNKNOWN
Platform: UNKNOWN
Classifier: Programming Language :: Python :: 3
Classifier: License :: OSI Approved :: GNU General Public License v3 or later (GPLv3+)
Classifier: Operating System :: OS Independent
Requires-Python: >=3.7
Requires-Dist: hyron
Requires-Dist: boto3
